japura/__init__.py
japura/efs.py
japura/key.py
japura/sql.py
japura-0.3.0.dist-info/LICENSE
japura-0.3.0.dist-info/METADATA
japura-0.3.0.dist-info/WHEEL
japura-0.3.0.dist-info/top_level.txt
japura-0.3.0.dist-info/RECORD
