Metadata-Version: 2.1
Name: japura
Version: 0.3.0
Summary: The Python library for securing and managing web resources.
Author-email: Joumaico Maulas <joumaico@gmx.com>
License: MIT License
Project-URL: Homepage, https://github.com/joumaico/japura/
Project-URL: Documentation, https://joumaico.github.io/japura/
Classifier: Development Status :: 5 - Production/Stable
Classifier: License :: OSI Approved :: MIT License
Classifier: Operating System :: OS Independent
Classifier: Programming Language :: Python
Classifier: Programming Language :: Python :: 3
Requires-Python: >=3.9
License-File: LICENSE
Requires-Dist: bcrypt (>=3.2.2)
Requires-Dist: cryptography (==37.0.4)
Requires-Dist: PyJWT (>=2.6.0)
Requires-Dist: pymysql (>=1.0.3)
